pymolstyles/__init__.py
pymolstyles/environment.py
pymolstyles/external/cgo_arrow.py
pymolstyles/plots.py
pymolstyles/resources.py
pymolstyles/styles.py
pymolstyles/tools.py
pymolstyles/workspace.py
pymolstyles-1.0.2.dist-info/LICENSE.md
pymolstyles-1.0.2.dist-info/METADATA
pymolstyles-1.0.2.dist-info/WHEEL
pymolstyles-1.0.2.dist-info/RECORD
