Metadata-Version: 2.1
Name: pymolstyles
Version: 1.0.2
Summary: Scripts for small molecule visualization using PyMOL
License: GNU GENERAL PUBLIC LICENSE V3
Author: Attilio Chiavegatti
Author-email: attiliochiavegatti@gmail.com
Requires-Python: >=3.9.0,<4.0.0
Classifier: License :: Other/Proprietary License
Classifier: Programming Language :: Python :: 3
Classifier: Programming Language :: Python :: 3.9
Classifier: Programming Language :: Python :: 3.10
Classifier: Programming Language :: Python :: 3.11
Requires-Dist: morfeus-ml (>=0.7.2,<0.8.0)
